[
 {
  "region": "Region (2)",
  "township": "Bago ",
  "office phone": "9977835728",
  "phone1": "0",
  "phone2": "0",
  "phone3 ": "0",
  "phone4": "0",
  "phone5": "0",
  "unavailable": "(Bago)∆မြို့ရှောင်လမ်း / မြို့ဦးကင်းတံတား / ရွှေပန်းရွာ / စိန်သာလျောင်းဘုရားအနောက်ဘက် / ကလိငါးပိပွဲရုံတန်း / မဇင်းဆည်ဘက် / ကတွင်းခြံဘက်။(Inndakaw)∆လှည်းကူး အင်းတိုင် / ဇရပ်ကွင်း / ဖောင်ကြီး / ထုံးကြီး ",
  "notes": "(Bago)∆စက်မှုဇုန်ဆိုလျှင် ဝန်းထိပ်အထိသာပို့ဆောင်ပေးပါသည် (ဝန်းထဲထိဝင်ပို့မပေးပါ)(Inndakaw)∆ဦးပိုင်စက်မှုဇုန် ဆိုလျှင် ဝန်းထိပ်ထိသာပိုဆောင်ပေးပါသည် (ဝန်းထဲဝင်ပို့မပေးပါ)",
  "available": "Bago/Inndakaw"
 },
 {
  "region": "Region (2)",
  "township": "KyoehPin Kyauk",
  "office phone": "9949044405",
  "phone1": "9941655501",
  "phone2": "0",
  "phone3 ": "0",
  "phone4": "0",
  "phone5": "0",
  "unavailable": "ဇီးကုန်းပါဆယ်များအား တိုးဂိတ်ထိသာပို့ဆောင်ပေးပါသည်",
  "notes": "ရွာပါဆယ်များဆိုလျှင် ရန်ကုန် ∆ ပြည် လမ်းမပေါ် ချိန်းပြီး လာယူနိင်ပါသည်",
  "available": "Kyopinkaut / ZeeKone /OkePho / AyeMyaTharyar"
 },
 {
  "region": "Region (2)",
  "township": "TharYarWaddy",
  "office phone": "9977835865",
  "phone1": "0",
  "phone2": "0",
  "phone3 ": "0",
  "phone4": "0",
  "phone5": "0",
  "unavailable": "(Tharyarwaddy)∆ဖားရွှေကျော် / တောင်စု / ဆရာစံကုန်း / ဖိုးခေါင် / စံရွေး။(Thonesal)∆ဘိုကြီးကုန်း၊ ကျွဲခြံအင်း၊ ငဖြူကလေးထိ ကားလမ်းဘေးတစ်လျှောက်သာပို့ဆောင်ပေးပါသည်။",
  "notes": "(Tharyarwaddy)∆အလယ်ကုန်းဆိုလျှင် ထန်းပင်ကုန်းထိသာပို့ဆောင်ပေးပါသည် / သာယာအေးဆိုလျှင် ရွာထိပ်ထိသာပို့ဆောင်ပေးပါသည် / ကားလမ်းနှင့်ဝေးသောရွာများအားပို့ဆောင်မပေးပါ။",
  "available": "Tharyarwaddy / Thonesal"
 },
 {
  "region": "Region (2)",
  "township": "Nyaung LayPin",
  "office phone": "9977835211",
  "phone1": "0",
  "phone2": "0",
  "phone3 ": "0",
  "phone4": "0",
  "phone5": "0",
  "unavailable": "(DaikOo / PyunTaSa)∆ ကျိုက်စကော / ကတုတ်ဘုရားကြီး။(NyaungLayPin)∆ ပိန်းဇလုပ် / ပဲနွယ်ကုန်း / ဖဒို။",
  "notes": "(DaikOo / PyunTaSa)∆ဖောင်တော်သီတံတားထိပ်ထိပဲပို့ပေးပါသည်။",
  "available": "DaikOo / PyunTaSa / NyaungLayPin"
 },
 {
  "region": "Region (2)",
  "township": "Pathein",
  "office phone": "9977835727",
  "phone1": "0",
  "phone2": "0",
  "phone3 ": "0",
  "phone4": "0",
  "phone5": "0",
  "unavailable": "ဘုရားကြီးကုန်း / ရွှေမြင်တင် / ငကျည်းထူ / စိန်ကုန်း / ပေါက်ကုန်း / သင်္ဘောကျဉ်းရဲစခန်း။",
  "notes": "0",
  "available": "0"
 },
 {
  "region": "Region (2)",
  "township": "Hinthada",
  "office phone": "9977835605",
  "phone1": "0",
  "phone2": "0",
  "phone3 ": "0",
  "phone4": "0",
  "phone5": "0",
  "unavailable": "ပိုက်တန်းရွာထဲ / ချောင်းဖျားလေး / denkoဆီဆိုင် / နတ်မော်",
  "notes": "တက္ကသိုလ်ဆိုလျှင် ကျောင်းပေါက်ဝထိသာ ပို့ပေးပါသည် / ဆေးရုံဆိုလျှင် ဆေးရုံဝန်းထိပ်ထိသာ ပို့ပေးပါသည် (ဆေးရုံအပေါ်ထိတက်မပေးပါ) / ဌာနဆိုင်ရာများ ရုံးအရှေ့ထိသာပို့ပေးပါသည် (ရုံးထဲဝင်ပို့မပေးပါ) ",
  "available": "0"
 },
 {
  "region": "Region (2)",
  "township": "Mubin",
  "office phone": "9946208782",
  "phone1": "0",
  "phone2": "0",
  "phone3 ": "0",
  "phone4": "0",
  "phone5": "0",
  "unavailable": "ရွှေတောင်မှော် / ထနီး / လေးအိမ်စု / မလတ်တို",
  "notes": "ရေလဲကလေးနဲ့အစိုးရနည်းပညာတက္ကသိုလ်ဘက်ကို Sunday တရက်ပဲဆင်းပေးပါသည် / ကျောင်းရွာဘက်ပါဆယ်များအား နီးစပ်ရာတွင်ချိန်းယူပေးရပါမည်။",
  "available": "0"
 },
 {
  "region": "Region (2)",
  "township": "ThanTwel",
  "office phone": "9977835873",
  "phone1": "0",
  "phone2": "0",
  "phone3 ": "0",
  "phone4": "0",
  "phone5": "0",
  "unavailable": "(Thantwel /Ngapali)∆စပါးကြီး / ဂေါ့ရွာ။",
  "notes": "သံတွဲဘက်ဆိုလျှင် ရွှေကျောင်းပြင်/အံတော်/ညောင်ပင်စျေး ထိသာပို့ပေးပါသည် / ငပလီဘက်ဆိုလျှင် မဇင်လေယာဉ်ကွင်းနားထိသာပို့ဆောင်ပေးပါသည်။",
  "available": "Thantwel /Ngapali"
  },
 {
  "region": "Region (2)",
  "township": "Sittwe",
  "office phone": "9977835508",
  "phone1": "0",
  "phone2": "0",
  "phone3 ": "0",
  "phone4": "0",
  "phone5": "0",
  "unavailable": "ကယ်ဆယ်ရေးမင်းဂံ / အောင်မင်္ဂလာရွာထဲဝင်ပို့မပေးပါ (နီးစပ်ရာတွင်ချိန်းယူပေးရပါမည်)",
  "notes": "စစ်တွေမင်းဂံဆိုလျှင် အကွက်(၈)အထိပဲပို့ပေးပါသည် / စစ်တွေမြို့၏အဆုံးဖြစ်သော ဆပ်ရိုးကျတံတားအထိသာပို့ဆောင်ပေးပါသည်။",
  "available": "0"
 },
 {
  "region": "Region (2)",
  "township": "Kyauk Phyu",
  "office phone": "9942880673",
  "phone1": "9972840648",
  "phone2": "0",
  "phone3 ": "0",
  "phone4": "0",
  "phone5": "0",
  "unavailable": "မင်းပြင် / ကုလာဘာ / ရေနံတောင် / ကျောက်ပြောက် / ငအုပ်။",
  "notes": "ဇင်ချောင်း / စနဲ ဘက်ဆိုလျှင် ကားဂိတ်ချပေးပါသည်။"
  "available": "0"
 }
  ]
